kong/__init__.py
kong/client.py
kong/errors.py
kong/request.py
kong/service/__init__.py
kong/service/base_service.py
kong/service/consumers.py
kong/service/node.py
python_kong_management-0.2.5.dist-info/DESCRIPTION.rst
python_kong_management-0.2.5.dist-info/METADATA
python_kong_management-0.2.5.dist-info/RECORD
python_kong_management-0.2.5.dist-info/WHEEL
python_kong_management-0.2.5.dist-info/metadata.json
python_kong_management-0.2.5.dist-info/top_level.txt
tests/__init__.py
tests/utils.py
tests/integration/__init__.py
tests/integration/test_service_consumer.py
tests/integration/test_service_node.py
tests/unit/__init__.py
tests/unit/test_service_node.py
