Metadata-Version: 2.0
Name: python-kong-management
Version: 0.2.5
Summary: Python api wrapper for Kong API Gateway
Home-page: https://github.com/mwisner/python-kong-management
Author: Matt Wisner
Author-email: mwisner@fourthlab.com
License: MIT license
Keywords: python-kong-management
Platform: UNKNOWN
Classifier: Development Status :: 2 - Pre-Alpha
Classifier: Intended Audience :: Developers
Classifier: License :: OSI Approved :: MIT License
Classifier: Natural Language :: English
Classifier: Programming Language :: Python :: 3
Classifier: Programming Language :: Python :: 3.3
Classifier: Programming Language :: Python :: 3.4
Classifier: Programming Language :: Python :: 3.5
Classifier: Programming Language :: Python :: 3.6
Requires-Dist: requests
